cxas/__init__.py
cxas/file_io.py
cxas/helper.py
cxas/label_mapper.py
cxas/segmentor.py
cxas/visualize.py
cxas/data/metainfo.json
cxas/data/paxray_labels.json
cxas/extraction/__init__.py
cxas/extraction/area.py
cxas/extraction/bounding_box.py
cxas/extraction/cardiothoracic_ratio.py
cxas/extraction/centroid.py
cxas/extraction/compactness.py
cxas/extraction/convexity.py
cxas/extraction/draw_helpers.py
cxas/extraction/func_helpers.py
cxas/extraction/perimeter.py
cxas/extraction/spinecenter_distance.py
cxas/io_utils/create_annotations.py
cxas/io_utils/dicomseg_2d.py
cxas/io_utils/mask_to_coco.py
cxas/models/__init__.py
cxas/models/UNet/backbone_unet.py
cxas/models/UNet/backbones.py
cxas/models/UNet/unet_components.py
cxas-0.0.17.data/scripts/cxas
cxas-0.0.17.data/scripts/cxas_feat_extract
cxas-0.0.17.data/scripts/cxas_segment
cxas-0.0.17.dist-info/LICENSE.txt
cxas-0.0.17.dist-info/METADATA
cxas-0.0.17.dist-info/WHEEL
cxas-0.0.17.dist-info/top_level.txt
cxas-0.0.17.dist-info/RECORD
