Metadata-Version: 2.1
Name: cxas
Version: 0.0.17
Summary: Segmentation of 159 anatomical classes for Chest X-Rays.
Home-page: https://github.com/ConstantinSeibold/ChestXRayAnatomySegmentation
Author: Constantin Seibold
Author-email: constantin.seibold2@uk-essen.de
License: UNKNOWN
Keywords: chest x-ray anatomy segmntation pytorch
Platform: UNKNOWN
Classifier: Development Status :: 3 - Alpha
Classifier: Intended Audience :: Science/Research
Classifier: Programming Language :: Python
Classifier: Topic :: Scientific/Engineering
Classifier: Operating System :: Unix
Classifier: License :: Free for non-commercial use
Requires-Python: >=3.9
License-File: LICENSE.txt
Requires-Dist: cython
Requires-Dist: torch
Requires-Dist: gdown
Requires-Dist: torchvision
Requires-Dist: numpy
Requires-Dist: SimpleITK
Requires-Dist: pydicom (==2.0.0)
Requires-Dist: pydicom-seg (==0.4.1)
Requires-Dist: scikit-image
Requires-Dist: scikit-learn
Requires-Dist: opencv-python
Requires-Dist: colorcet
Requires-Dist: pycocotools
Requires-Dist: pandas
Requires-Dist: tqdm
